[
  {
    "id": 1,
    "name": "Яйца",
    "emoji": "🥚",
    "category": "Молочные продукты",
    "categoryEmoji": "🥛",
    "frequency": 0.98
  },
  {
    "id": 2,
    "name": "Молоко",
    "emoji": "🥛",
    "category": "Молочные продукты",
    "categoryEmoji": "🥛",
    "frequency": 0.9
  },
  {
    "id": 3,
    "name": "Сыр",
    "emoji": "🧀",
    "category": "Молочные продукты",
    "categoryEmoji": "🥛",
    "frequency": 0.85
  },
  {
    "id": 4,
    "name": "Картофель",
    "emoji": "🥔",
    "category": "Овощи",
    "categoryEmoji": "🥦",
    "frequency": 0.95
  },
  {
    "id": 5,
    "name": "Лук репчатый",
    "emoji": "🧅",
    "category": "Овощи",
    "categoryEmoji": "🥦",
    "frequency": 0.92
  },
  {
    "id": 6,
    "name": "Морковь",
    "emoji": "🥕",
    "category": "Овощи",
    "categoryEmoji": "🥦",
    "frequency": 0.88
  },
  {
    "id": 7,
    "name": "Помидоры",
    "emoji": "🍅",
    "category": "Овощи",
    "categoryEmoji": "🥦",
    "frequency": 0.82
  },
  {
    "id": 8,
    "name": "Огурцы",
    "emoji": "🥒",
    "category": "Овощи",
    "categoryEmoji": "🥦",
    "frequency": 0.8
  },
  {
    "id": 9,
    "name": "Чеснок",
    "emoji": "🧄",
    "category": "Овощи",
    "categoryEmoji": "🥦",
    "frequency": 0.78
  },
  {
    "id": 10,
    "name": "Капуста",
    "emoji": "🥬",
    "category": "Овощи",
    "categoryEmoji": "🥦",
    "frequency": 0.75
  },
  {
    "id": 11,
    "name": "Курица",
    "emoji": "🍗",
    "category": "Мясо и птица",
    "categoryEmoji": "🥩",
    "frequency": 0.9
  },
  {
    "id": 12,
    "name": "Говядина",
    "emoji": "🥩",
    "category": "Мясо и птица",
    "categoryEmoji": "🥩",
    "frequency": 0.7
  },
  {
    "id": 13,
    "name": "Свинина",
    "emoji": "🥓",
    "category": "Мясо и птица",
    "categoryEmoji": "🥩",
    "frequency": 0.65
  },
  {
    "id": 14,
    "name": "Фарш мясной",
    "emoji": "🍖",
    "category": "Мясо и птица",
    "categoryEmoji": "🥩",
    "frequency": 0.6
  },
  {
    "id": 15,
    "name": "Рис",
    "emoji": "🍚",
    "category": "Крупы и макароны",
    "categoryEmoji": "🌾",
    "frequency": 0.85
  },
  {
    "id": 16,
    "name": "Макароны",
    "emoji": "🍜",
    "category": "Крупы и макароны",
    "categoryEmoji": "🌾",
    "frequency": 0.83
  },
  {
    "id": 17,
    "name": "Гречка",
    "emoji": "🌾",
    "category": "Крупы и макароны",
    "categoryEmoji": "🌾",
    "frequency": 0.75
  },
  {
    "id": 18,
    "name": "Мука",
    "emoji": "🌾",
    "category": "Крупы и макароны",
    "categoryEmoji": "🌾",
    "frequency": 0.7
  },
  {
    "id": 19,
    "name": "Хлеб",
    "emoji": "🍞",
    "category": "Хлебобулочные",
    "categoryEmoji": "🥖",
    "frequency": 0.95
  },
  {
    "id": 20,
    "name": "Масло сливочное",
    "emoji": "🧈",
    "category": "Жиры и масла",
    "categoryEmoji": "🫒",
    "frequency": 0.88
  },
  {
    "id": 21,
    "name": "Масло растительное",
    "emoji": "🫒",
    "category": "Жиры и масла",
    "categoryEmoji": "🫒",
    "frequency": 0.92
  },
  {
    "id": 22,
    "name": "Сахар",
    "emoji": "🍚",
    "category": "Специи и добавки",
    "categoryEmoji": "🧂",
    "frequency": 0.85
  },
  {
    "id": 23,
    "name": "Соль",
    "emoji": "🧂",
    "category": "Специи и добавки",
    "categoryEmoji": "🧂",
    "frequency": 0.99
  },
  {
    "id": 24,
    "name": "Перец",
    "emoji": "🌶️",
    "category": "Специи и добавки",
    "categoryEmoji": "🧂",
    "frequency": 0.8
  },
  {
    "id": 25,
    "name": "Томатная паста",
    "emoji": "🥫",
    "category": "Консервы и соусы",
    "categoryEmoji": "🍶",
    "frequency": 0.7
  },
  {
    "id": 26,
    "name": "Майонез",
    "emoji": "🍶",
    "category": "Консервы и соусы",
    "categoryEmoji": "🍶",
    "frequency": 0.65
  },
  {
    "id": 27,
    "name": "Сметана",
    "emoji": "🥛",
    "category": "Молочные продукты",
    "categoryEmoji": "🥛",
    "frequency": 0.75
  },
  {
    "id": 28,
    "name": "Творог",
    "emoji": "🧀",
    "category": "Молочные продукты",
    "categoryEmoji": "🥛",
    "frequency": 0.6
  },
  {
    "id": 29,
    "name": "Кефир",
    "emoji": "🥛",
    "category": "Молочные продукты",
    "categoryEmoji": "🥛",
    "frequency": 0.55
  },
  {
    "id": 30,
    "name": "Рыба",
    "emoji": "🐟",
    "category": "Рыба и морепродукты",
    "categoryEmoji": "🦐",
    "frequency": 0.6
  },
  {
    "id": 31,
    "name": "Яблоки",
    "emoji": "🍎",
    "category": "Фрукты",
    "categoryEmoji": "🍎",
    "frequency": 0.7
  },
  {
    "id": 32,
    "name": "Бананы",
    "emoji": "🍌",
    "category": "Фрукты",
    "categoryEmoji": "🍎",
    "frequency": 0.65
  },
  {
    "id": 33,
    "name": "Лимон",
    "emoji": "🍋",
    "category": "Фрукты",
    "categoryEmoji": "🍎",
    "frequency": 0.5
  },
  {
    "id": 34,
    "name": "Зелень",
    "emoji": "🌿",
    "category": "Овощи",
    "categoryEmoji": "🥦",
    "frequency": 0.6
  },
  {
    "id": 35,
    "name": "Грибы",
    "emoji": "🍄",
    "category": "Овощи",
    "categoryEmoji": "🥦",
    "frequency": 0.5
  },
  {
    "id": 36,
    "name": "Болгарский перец",
    "emoji": "🫑",
    "category": "Овощи",
    "categoryEmoji": "🥦",
    "frequency": 0.55
  },
  {
    "id": 37,
    "name": "Сосиски",
    "emoji": "🌭",
    "category": "Мясо и птица",
    "categoryEmoji": "🥩",
    "frequency": 0.6
  },
  {
    "id": 38,
    "name": "Колбаса",
    "emoji": "🍖",
    "category": "Мясо и птица",
    "categoryEmoji": "🥩",
    "frequency": 0.58
  },
  {
    "id": 39,
    "name": "Бекон",
    "emoji": "🥓",
    "category": "Мясо и птица",
    "categoryEmoji": "🥩",
    "frequency": 0.45
  },
  {
    "id": 40,
    "name": "Свекла",
    "emoji": "🍠",
    "category": "Овощи",
    "categoryEmoji": "🥦",
    "frequency": 0.5
  },
  {
    "id": 41,
    "name": "Лук зеленый",
    "emoji": "🌱",
    "category": "Овощи",
    "categoryEmoji": "🥦",
    "frequency": 0.4
  },
  {
    "id": 42,
    "name": "Овсяные хлопья",
    "emoji": "🌾",
    "category": "Крупы и макароны",
    "categoryEmoji": "🌾",
    "frequency": 0.55
  },
  {
    "id": 43,
    "name": "Консервированная кукуруза",
    "emoji": "🌽",
    "category": "Консервы и соусы",
    "categoryEmoji": "🍶",
    "frequency": 0.4
  },
  {
    "id": 44,
    "name": "Консервированный горошек",
    "emoji": "🫛",
    "category": "Консервы и соусы",
    "categoryEmoji": "🍶",
    "frequency": 0.35
  },
  {
    "id": 45,
    "name": "Уксус",
    "emoji": "🍶",
    "category": "Специи и добавки",
    "categoryEmoji": "🧂",
    "frequency": 0.5
  },
  {
    "id": 46,
    "name": "Горчица",
    "emoji": "🟡",
    "category": "Специи и добавки",
    "categoryEmoji": "🧂",
    "frequency": 0.4
  },
  {
    "id": 47,
    "name": "Кетчуп",
    "emoji": "🍅",
    "category": "Консервы и соусы",
    "categoryEmoji": "🍶",
    "frequency": 0.45
  },
  {
    "id": 48,
    "name": "Соевый соус",
    "emoji": "🍶",
    "category": "Консервы и соусы",
    "categoryEmoji": "🍶",
    "frequency": 0.4
  },
  {
    "id": 49,
    "name": "Мед",
    "emoji": "🍯",
    "category": "Специи и добавки",
    "categoryEmoji": "🧂",
    "frequency": 0.45
  },
  {
    "id": 50,
    "name": "Чай",
    "emoji": "☕",
    "category": "Напитки",
    "categoryEmoji": "🧃",
    "frequency": 0.95
  }
]
